CHANGES
LICENSE
MANIFEST.in
README.rst
requirements-tox.txt
requirements.txt
setup.cfg
setup.py
bin/py-skeleton.py
py_skeleton/__init__.py
py_skeleton/utilities.py
py_skeleton.egg-info/PKG-INFO
py_skeleton.egg-info/SOURCES.txt
py_skeleton.egg-info/dependency_links.txt
py_skeleton.egg-info/requires.txt
py_skeleton.egg-info/top_level.txt
tests/__init__.py
tests/test_utilities.py